metalearn/__init__.py
metalearn/metafeatures/__init__.py
metalearn/metafeatures/base.py
metalearn/metafeatures/common_operations.py
metalearn/metafeatures/constants.py
metalearn/metafeatures/decision_tree_metafeatures.py
metalearn/metafeatures/general_resource_computers.py
metalearn/metafeatures/information_theoretic_metafeatures.py
metalearn/metafeatures/landmarking_metafeatures.py
metalearn/metafeatures/metafeatures.py
metalearn/metafeatures/metafeatures_schema.json
metalearn/metafeatures/simple_metafeatures.py
metalearn/metafeatures/static_assets.py
metalearn/metafeatures/statistical_metafeatures.py
metalearn/metafeatures/text_metafeatures.py
metalearn-0.6.2.dist-info/LICENSE
metalearn-0.6.2.dist-info/METADATA
metalearn-0.6.2.dist-info/WHEEL
metalearn-0.6.2.dist-info/top_level.txt
metalearn-0.6.2.dist-info/RECORD
