Metadata-Version: 2.1
Name: metalearn
Version: 0.6.2
Summary: A package to aid in metalearning
Home-page: https://github.com/byu-dml/metalearn
Author: Roland Laboulaye, Brandon Schoenfeld, Casey Davis
Author-email: rlaboulaye@gmail.com, bjschoenfeld@gmail.com, caseykdavis@gmail.com
License: MIT
Download-URL: https://github.com/byu-dml/metalearn/archive/0.6.2.tar.gz
Keywords: metalearning,machine learning,metalearn
Platform: UNKNOWN
Classifier: Programming Language :: Python :: 3
Requires-Dist: numpy
Requires-Dist: pandas
Requires-Dist: scikit-learn (<=0.22.2.post1)
